redis_bandit/__init__.py
redis_bandit/base.py
redis_bandit/epsilon_greedy.py
redis_bandit/py.typed
redis_bandit-0.1.0.dist-info/LICENSE
redis_bandit-0.1.0.dist-info/WHEEL
redis_bandit-0.1.0.dist-info/METADATA
redis_bandit-0.1.0.dist-info/RECORD
