Metadata-Version: 2.1
Name: redis-bandit
Version: 0.1.0
Summary: A Python, redis-backed, distributed Multi-Armed Bandit Framework. The goal is being able to scale a MAB horizontally.
Home-page: https://github.com/deeplearningbrasil/redis-bandit
License: Apache Software License 2.0
Keywords: machine learning,reinforcemente learning,multi-armed bandit,redis
Author: fernandocamargoai
Author-email: fernando.camargo.ai@gmail.com
Requires-Python: >=3.7,<4.0
Classifier: Development Status :: 3 - Alpha
Classifier: Intended Audience :: Developers
Classifier: License :: Other/Proprietary License
Classifier: Operating System :: OS Independent
Classifier: Programming Language :: Python :: 3
Classifier: Programming Language :: Python :: 3.10
Classifier: Programming Language :: Python :: 3.7
Classifier: Programming Language :: Python :: 3.8
Classifier: Programming Language :: Python :: 3.9
Classifier: Topic :: Scientific/Engineering :: Artificial Intelligence
Classifier: Topic :: Software Development :: Libraries :: Python Modules
Requires-Dist: importlib_metadata (>=4.5.0,<5.0.0); python_version < "3.8"
Requires-Dist: pydantic (>=1.8)
Requires-Dist: redis (>=3.5)
Requires-Dist: walrus (>=0.8)
Project-URL: Repository, https://github.com/deeplearningbrasil/redis-bandit
